README.md
setup.py
apmath/__init__.py
apmath/apmath.py
apmath.egg-info/PKG-INFO
apmath.egg-info/SOURCES.txt
apmath.egg-info/dependency_links.txt
apmath.egg-info/requires.txt
apmath.egg-info/top_level.txt