Metadata-Version: 2.1
Name: apmath
Version: 0.0.2
Summary: Mathematical apmath for python.
Author: Aleksander Paradiuk
Author-email: olekparadiuk@gmail.com
License: MIT
